<?xml version="1.0" encoding="utf-8"?>
<odoo>
    <data>
    
        <record id="master_registration_view_tree" model="ir.ui.view">
            <field name="name">master.registration.view.tree</field>
            <field name="model">master.registration</field>
            <field name="arch" type="xml">
                <tree string="Daftar Registrasi" js_class="master_registration_list_dashboard">
                    <field name="status_antrian" string="Status Antrian" decoration-success="status_antrian == 'done'" decoration-warning="status_antrian == 'waiting'" decoration-danger="status_antrian == 'progress'" widget="badge"/>
                    <field name="name" />
                    <field name="no_antrian" />
                    <field name="no_registrasi" invisible="1"/>
                    <field name="no_medical_report" />
                    <field name="on_progress" />
                    <field name="pasien_id" />
                    <field name="jenis_kelamin" string="L/P"/>
                    <field name="umur" />
                    <field name="status_kunjungan" decoration-info="status_kunjungan == 'tanpa'" decoration-success="status_kunjungan == 'perjanjian'" decoration-warning="status_kunjungan == 'prioritas'" widget="badge"/>
                    <field name="jenis_perjanjian" decoration-success="jenis_perjanjian == 'mc'" decoration-info="jenis_perjanjian == 'mcu'" decoration-warning="jenis_perjanjian == 'onsite'" widget="badge"/>
                    <field name="state" decoration-success="state == 'confirm'" decoration-warning="state == 'going'" decoration-info="state == 'draft'" decoration-danger="state == 'cancel'" widget="badge"/>
                    <field name="faskes_id" />
                    <field name="tanggal_registrasi" />
                    <button string="Cek Status" name="status_pemeriksaan_wizard" type="object" class="oe_highlight" attrs="{'invisible' : [('state', 'in', ['draft', 'done', 'cancel'])]}" context="{'registration_id' : active_id, 'is_status' : 1}"/>
                </tree>
            </field>
        </record>

        <record id="master_registration_view_form" model="ir.ui.view">
            <field name="name">master.registration.view.form</field>
            <field name="model">master.registration</field>
            <field name="arch" type="xml">
                <form string="Data Registrasi" duplicate="0">

                    <header>
                        <field name="list_package_ids" invisible="1"/>
                        <field name="package_mcu_ids" invisible="1"/>
                        <field name="perusahaan_ids" invisible="1"/>
                        <field name="poli_ids" invisible="1"/>
                        <field name="dokter_ids" invisible="1"/>
                        <field name="examination_ids" invisible="1"/>
                        <field name="filter_examination_ids" invisible="1"/>
                        <field name="status_kunjungan_ids" invisible="1"/>
                        <field name="is_makan" invisible="1"/>
                        <button name="action_set_to_draft" type="object" states="confirm" string="Set to Draft" class="btn btn-info"/>
                        <button name="action_confirm" type="object" states="draft" string="Confirm" class="btn btn-success" />
                        <button name="action_cancel" type="object" states="confirm" string="Cancel" class="btn btn-danger" />
                        <button name="print_data_pasien" type="object" string="Cetak" class="oe_highlight" attrs="{'invisible':['|', ('state', '!=', 'confirm'), ('jenis_perjanjian', 'not in', ['mcu', 'onsite'])]}" />
                        <field name="state" widget="statusbar" statusbar_visible="draft,confirm,cancel"/>
                    </header>

                    <sheet>
                        <group col="6" colspan="2" style="margin: 1px 0px;">
                            <div class="oe_title" style="margin: 0px 0px 0px 0px;">
                                <label for="name" string="No. Registrasi"/>
                                <h1>
                                    <field name="name"/>
                                </h1>
                            </div>

                            <div class="oe_title" style="margin: 0px 0px 0px 200px;">
                                <label for="no_antrian" string="No. Antrian"/>
                                <h1 class="text-center" style="width:70px;">
                                    <field name="no_antrian" force_save="1"/>
                                </h1>
                            </div>

                            <div class="oe_title">
                                <field name="image_1920" force_save="1" nolabel="1" widget='image' class="oe_avatar"/>
                            </div>
                        </group>

                        <group col="4" colspan="2" style="margin: 1px 0px;">
                            <field name="tanggal_registrasi" required="1" />
                            <field name="tipe_transaksi" required="1" />
                            <field name="status_kunjungan" />
                            <field name="jenis_perjanjian" required="1" force_save="1" attrs="{'readonly' : ['|', ('status_kunjungan', 'in', ['perjanjian', 'prioritas']), ('state', '!=', 'draft')]}" />
                            <field name="reservation_id" domain="[('id', 'in', status_kunjungan_ids)]" attrs="{'invisible' : [('status_kunjungan', 'not in', ['perjanjian', 'prioritas'])], 'required' : [('status_kunjungan', 'in', ['perjanjian', 'prioritas'])]}" options="{'no_open': True, 'no_create': True, 'no_create_edit':True, 'no_quick_create': True}"/>
                        </group>

                        <group style="margin: 1px 0px;">
                            <group string="Data Pasien" style="margin: 1px 0px;">
                                <field name="no_record" force_save="1" invisible="1"/>
                                <field name="no_registrasi" force_save="1" invisible="1"/>
                                <field name="no_medical_report" force_save="1" attrs="{'invisible' : [('pasien_id', '=', False)]}"/>
                                <field name="display_name" force_save="1" invisible="1"/>
                                <field name="state_name" force_save="1" invisible="1"/>
                                <field name="country_name" force_save="1" invisible="1"/>
                                <field name="city_name" force_save="1" invisible="1"/>
                                <field name="kecamatan_name" force_save="1" invisible="1"/>
                                <field name="kelurahan_name" force_save="1" invisible="1"/>
                                <field name="pasien_id" force_save="1" attrs="{'readonly' : ['|', ('status_kunjungan', 'in', ['perjanjian', 'prioritas']), ('state', '!=', 'draft')], 'required' : [('status_kunjungan', '=', 'tanpa')]}" context="{'tree_view_ref': 'asb_klinik_master_personil.master_pasien_view_template_tree', 'form_view_ref': 'asb_klinik_master_personil.master_pasien_view_form', 'default_customer': 0, 'default_supplier': 0, 'default_is_company': 0, 'default_is_pasien' : 1, 'default_type' : ''}" options="{'no_quick_create': True}"/>
                                <field name="no_ktp" force_save="1" attrs="{'invisible' : [('pasien_id', '=', False)]}"/>
                                <field name="warga_negara" force_save="1" attrs="{'invisible' : [('pasien_id', '=', False)]}"/>
                                <field name="jenis_kelamin" force_save="1" attrs="{'invisible' : [('pasien_id', '=', False)]}"/>
                                <field name="tempat_lahir" force_save="1" attrs="{'invisible' : [('pasien_id', '=', False)]}"/>
                                <field name="tanggal_lahir" force_save="1" attrs="{'invisible' : [('pasien_id', '=', False)]}"/>
                                <field name="umur" force_save="1" attrs="{'invisible' : [('pasien_id', '=', False)]}"/>
                                <field name="email" force_save="1" widget="email" attrs="{'invisible' : [('pasien_id', '=', False)]}"/>
                                <field name="mobile" force_save="1" widget="mobile" attrs="{'invisible' : [('pasien_id', '=', False)]}"/>
                                <span class="o_form_label o_td_label" name="address_name" attrs="{'invisible' : [('pasien_id', '=', False)]}">Address</span>
                                <div class="o_address_format" attrs="{'invisible' : [('pasien_id', '=', False)]}">
                                    <field name="street" force_save="1" readonly="1" class="o_address_street" placeholder="Street..." />
                                    <field name="kelurahan_id" force_save="1" readonly="1" class="o_address_city" placeholder="Kelurahan" options="{'no_open': True, 'no_create': True}" domain="[('kecamatan_id', '=', kecamatan_id)]" context="{'tree_view_ref' : 'asb_state_city.kelurahan_ref_view_tree'}" />
                                    <field name="kecamatan_id" force_save="1" readonly="1"  class="o_address_state" placeholder="Kecamatan" options="{'no_open': True, 'no_create': True}" domain="[('city_id', '=', city_id)]" context="{'tree_view_ref' : 'asb_state_city.kecamatan_ref_view_tree'}" />
                                    <field name="city_id" force_save="1" readonly="1" class="o_address_city" placeholder="City" options="{'no_open': True, 'no_create': True}" domain="[('state_id', '=', state_id)]" context="{'tree_view_ref' : 'asb_state_city.kota_kabupaten_ref_view_tree'}" />
                                    <field name="state_id" force_save="1" readonly="1" class="o_address_state" placeholder="State" options="{'no_open': True, 'no_create': True}" domain="[('country_id', '=', country_id)]" />
                                    <field name="country_id" force_save="1" readonly="1" class="o_address_city" placeholder="Country" options="{'no_open': True, 'no_create': True}" />
                                    <field name="zip" force_save="1" readonly="1" class="o_address_state" placeholder="ZIP" />
                                </div>
                                <field name="is_perjanjian" invisible="1" force_save="1" readonly="1"/>
                                <field name="is_perjanjian_mcu" invisible="1" force_save="1" readonly="1"/>
                            </group>

                            <group string="Informasi Layanan" style="margin: 1px 0px;">
                                <field name="status_gl" force_save="1" attrs="{'readonly' : ['|', ('status_kunjungan', 'in', ['perjanjian', 'prioritas']), ('state', '!=', 'draft')]}" />
                                <field name="no_gl" force_save="1" attrs="{'invisible' : [('status_gl', 'in', ['tidak', False])], 'required' : [('status_gl', '=', 'ya')], 'readonly' : ['|', ('status_kunjungan', 'in', ['perjanjian', 'prioritas']), ('state', '!=', 'draft')]}"/>
                                <field name="tipe_pengiriman" required="1" force_save="1" attrs="{'readonly' : ['|', ('status_kunjungan', 'in', ['perjanjian', 'prioritas']), ('state', '!=', 'draft')]}" />
                                <field name="bahasa_hasil" force_save="1" attrs="{'readonly' : ['|', ('status_kunjungan', 'in', ['perjanjian', 'prioritas']), ('state', '!=', 'draft')]}" />
                                <field name="poli_unit_ids" force_save="1" domain="[('id', 'in', poli_ids)]" attrs="{'invisible' : [('jenis_perjanjian', 'not in', ['mc'])], 'required' : [('jenis_perjanjian', '=', 'mc')], 'readonly' : ['|', ('status_kunjungan', 'in', ['perjanjian', 'prioritas']), ('state', '!=', 'draft')]}" widget="many2many_tags" options="{'no_open': True, 'no_create': True, 'no_create_edit':True, 'no_quick_create': True, 'color_field': 'color'}"/>
                                <field name="dokter_id" force_save="1" domain="[('id', 'in', dokter_ids)]" attrs="{'invisible' : ['|', ('jenis_perjanjian', 'not in', ['mc']), ('poli_unit_ids', '=', [])], 'readonly': ['|', '|', ('status_kunjungan', 'in', ['perjanjian', 'prioritas']), ('poli_unit_ids', '=', []), ('state', '!=', 'draft')], 'required' : ['&amp;', '&amp;', ('status_kunjungan', '=', 'tanpa'), ('jenis_perjanjian', '=', 'mc'), ('is_perjanjian_mcu', '=', True)]}" options="{'no_open': True, 'no_create': True, 'no_create_edit':True, 'no_quick_create': True}"/>
                                <field name="nama_dokter" force_save="1" invisible="1"/>
                                <field name="kode" force_save="1" invisible="1"/>
                                <field name="package_mcu_id" force_save="1" domain="[('id', 'in', package_mcu_ids)]" attrs="{'invisible' : [('jenis_perjanjian', 'not in', ['mcu', 'onsite'])], 'readonly': ['|', '|', ('perusahaan_id', '=', False), ('status_kunjungan', 'in', ['perjanjian', 'prioritas']), ('state', '!=', 'draft')]}" options="{'no_open': True, 'no_create': True, 'no_create_edit':True, 'no_quick_create': True}"/>
                                <field name="list_package_id" force_save="1" domain="[('id', 'in', list_package_ids)]" attrs="{'invisible' : ['|', ('jenis_perjanjian', 'not in', ['mcu', 'onsite']), ('package_mcu_id', '=', False)], 'readonly' : ['|', ('status_kunjungan', 'in', ['perjanjian', 'prioritas']), ('state', '!=', 'draft')]}" options="{'no_open': True, 'no_create': True, 'no_create_edit':True, 'no_quick_create': True}"/>
                                <field name="certificate_ids" force_save="1" widget="many2many_tags" options="{'color_field': 'color'}" attrs="{'invisible' : ['|', '|', ('jenis_perjanjian', 'not in', ['mcu', 'onsite']), ('package_mcu_id', '=', False), ('list_package_id', '=', False)]}"/>
                                <field name="tanggal_pembuatan" force_save="1" invisible="1"/>
                                <field name="user_create" force_save="1" invisible="1"/>
                                <field name="tanggal_confirm" force_save="1" invisible="1"/>
                                <field name="user_approve" force_save="1" invisible="1"/>
                                <field name="currency_id" invisible="1"/>
                                <field name="faskes_id" force_save="1" invisible="1"/>
                                <field name="code" force_save="1" invisible="1"/>
                                <field name="on_progress" force_save="1" invisible="1"/>
                                <field name="status_antrian" invisible="1"/>
                                <field name="is_blood_group_fasting" invisible="1"/>
                                <field name="is_blood_group_prandial" invisible="1"/>
                                <field name="status_pp" invisible="1"/>
                                <field name="waktu_cek_lab" invisible="1"/>
                            </group>
                        </group>

                        <notebook>
                            <page name="informasi_pekerjaan" string="Informasi Pekerjaan">
                                <group col="4" colspan="2" attrs="{'invisible' : [('pasien_id', '=', False)]}">
                                    <field name="perusahaan_id" attrs="{'readonly' : ['|', ('status_kunjungan', 'in', ['perjanjian', 'prioritas']), ('state', '!=', 'draft')]}" force_save="1" domain="[('id', 'in', perusahaan_ids)]" options="{'no_open': True, 'no_create': True, 'no_create_edit':True, 'no_quick_create': True}" context="{'tree_view_ref': 'asb_klinik_master_personil.master_perusahaan_view_template_tree'}"/>
                                    <field name="nik_pegawai" force_save="1" />
                                    <field name="status_pegawai" force_save="1" />
                                    <field name="mulai_bekerja" force_save="1" />
                                    <field name="jenis_pekerjaan_id" force_save="1" options="{'no_open': True, 'no_create': True, 'no_create_edit':True, 'no_quick_create': True}"/>
                                    <field name="shift_kerja" force_save="1" />
                                    <field name="lokasi_pekerjaan_id" force_save="1" options="{'no_open': True}" />
                                    <field name="function" force_save="1" />
                                </group>
                            </page>
                            <page name="detail_pemeriksaan" string="Detail Pemeriksaan">
                                <field name="fixed_costing_line" force_save="1" attrs="{'invisible' : [('jenis_perjanjian', 'not in', ['mcu', 'onsite'])]}">
                                    <tree>
                                        <field name="fixed_costing_id"/>
                                        <field name="name" invisible = "1"/>
                                        <field name="cost_onsite" widget="monetary" invisible = "1"/>
                                        <field name="cost_in_house" widget="monetary" invisible = "1"/>
                                    </tree>
                                    <form string="Fixed Costing" readonly="1" force_save="1">
                                        <sheet>
                                            <group col="4" colspan="2">
                                                <field name="fixed_costing_id" />
                                            </group>
                                        </sheet>
                                    </form>
                                </field>

                                <field name="examination_list_ids" domain="[('id', 'in', examination_ids)]" attrs="{'invisible' : [('is_perjanjian', '=', False)], 'readonly' : ['|', ('state', '!=', 'draft'), '&amp;', ('is_perjanjian_mcu', '=', True), ('is_perjanjian', '=', True)]}" widget="many2many" options="{'no_create': True}" force_save="1" context="{'tree_view_ref': 'asb_klinik_master_product.examination_list_view_tree'}">
                                    <tree>
                                        <field name="name" string="Nama Pemeriksaan"/>
                                        <field name="poli_unit_id" string="Poli / Unit"/>
                                        <field name="list_price" string="Harga Jual" widget="monetary" invisible="1"/>
                                        <field name="total_beban_langsung" widget="monetary" invisible="1"/>
                                    </tree>
                                    <form string="Examination List">
                                        <sheet>
                                            <group col="4" colspan="2">
                                                <field name="name" />
                                                <field name="poli_unit_id"/>
                                            </group>
                                        </sheet>
                                    </form>
                                </field>

                                <field name="sampling_list_ids" widget="many2many" options="{'no_create': True}" force_save="1" attrs="{'invisible' : [('jenis_perjanjian', 'not in', ['mcu', 'onsite'])]}">
                                    <tree>
                                        <field name="name" string="Sampling"/>
                                        <field name="total_cost" string="Cost" widget="monetary" invisible="1"/>
                                    </tree>
                                    <form string="Sampling List">
                                        <sheet>
                                            <field name="name" string="Sampling"/>
                                            <field name="total_cost" string="Cost" widget="monetary"/>
                                        </sheet>
                                    </form>
                                </field>
                            </page>
                            <page name="additional_examination_list" string="Additional Examination List for MCU" attrs="{'invisible' : [('jenis_perjanjian', 'not in', ['mcu', 'onsite'])]}">
                                <field name="additional_examination_ids" domain="[('id', 'in', filter_examination_ids)]" widget="many2many" options="{'no_create': True}" force_save="1" context="{'tree_view_ref': 'asb_klinik_master_product.examination_list_view_tree'}">
                                    <tree>
                                        <field name="name" string="Nama Pemeriksaan"/>
                                        <field name="poli_unit_id" string="Poli / Unit"/>
                                        <field name="list_price" string="Harga Jual" widget="monetary" invisible="1"/>
                                    </tree>
                                    <form string="Examination List">
                                        <sheet>
                                            <group col="4" colspan="2">
                                                <field name="name" />
                                                <field name="poli_unit_id"/>
                                            </group>
                                        </sheet>
                                    </form>
                                </field>
                            </page>
                        </notebook>
                        <div class="row" invisible = "1">
                            <div class="col-md-10 text-right">
                                <h5>Total Cost Pemeriksaan (IDR)</h5>
                            </div>

                            <div class="col-md-2 text-left">
                                <h5>
                                    <field name="total_cost_examination_list" force_save="1" widget="monetary" class="oe_inline" />
                                </h5>
                            </div>
                        </div>

                        <div class="row" attrs="{'invisible' : ['|', '|', ('jenis_perjanjian', 'not in', ['mcu', 'onsite']), ('package_mcu_id', '=', False), ('list_package_id', '=', False)]}">
                            <div class="col-md-10 text-right">
                                <h5>Total Price Paket MCU (IDR)</h5>
                            </div>

                            <div class="col-md-2 text-left">
                                <h5>
                                    <field name="price_paket" force_save="1" widget="monetary" class="oe_inline" />
                                </h5>
                            </div>
                        </div>

                        <div class="row" attrs="{'invisible' : ['|', '|', ('jenis_perjanjian', '=', 'mc'), ('is_perjanjian_mcu', '=', False), ('is_perjanjian', '=', False)]}">
                            <div class="col-md-10 text-right">
                                <h5>Total Cost Additional Examination List (IDR)</h5>
                            </div>

                            <div class="col-md-2 text-left">
                                <h5>
                                    <field name="total_cost_examination_ids" force_save="1" widget="monetary" class="oe_inline" />
                                </h5>
                            </div>
                        </div>

                        <div class="row" invisible = "1">
                            <div class="col-md-10 text-right">
                                <h5>Total Cost Sampling (IDR)</h5>
                            </div>

                            <div class="col-md-2 text-left">
                                <h5>
                                    <field name="total_cost_sampling" force_save="1" widget="monetary" class="oe_inline" />
                                </h5>
                            </div>
                        </div>

                        <div class="row" attrs="{'invisible' : ['|', '|', ('jenis_perjanjian', '=', 'mc'), ('is_perjanjian_mcu', '=', False), ('is_perjanjian', '=', False)]}">
                            <div class="col-md-10 text-right">
                                <h5>Total Cost Keseluruhan (IDR)</h5>
                            </div>

                            <div class="col-md-2 text-left">
                                <h5>
                                    <field name="total_cost" force_save="1" widget="monetary" class="oe_inline" />
                                </h5>
                            </div>
                        </div>
                    </sheet>

                    <div class="oe_chatter">
                        <field name="message_follower_ids" widget="mail_followers"/>
                        <field name="message_ids" widget="mail_thread"/>
                    </div>
                    
                </form>
            </field>
        </record>

        <record id="view_master_registration_filter" model="ir.ui.view">
            <field name="name">master.registration.view.search</field>
            <field name="model">master.registration</field>
            <field name="arch" type="xml">

                <search string="Search Registrasi">
                    <field name="name" string="Nama Pasien" filter_domain="['|', ('display_name', 'ilike', self), ('name', 'ilike', self)]"/>
                    <field name="no_ktp" string="No. KTP Pasien" filter_domain="[('no_ktp', 'ilike', self)]"/>
                    <field name="tanggal_registrasi" string="Tanggal Reservasi" filter_domain="[('tanggal_registrasi', '=', self)]"/>
                    <field name="jenis_perjanjian" string="Jenis Perjanjian" filter_domain="[('jenis_perjanjian', '=', self)]"/>
                    <separator/>
                    <filter name="today" string="Today" domain="[('tanggal_registrasi', '=', datetime.datetime.now())]"/>
                    <separator/>
                    <filter name="draft_registrasi" string="Waiting List" domain="[('state', '=', 'draft')]"/>
                    <filter name="total_mc" string="Total MC" domain="[('tipe_transaksi', '=', 'mc')]"/>
                    <filter name="total_mcu" string="Total MCU" domain="[('tipe_transaksi', 'in', ['mcu', 'onsite', 'provider'])]"/>
                </search>

            </field>
        </record>

        <record id="master_registration_action" model="ir.actions.act_window">
            <field name="name">Daftar Registrasi</field>
            <field name="type">ir.actions.act_window</field>
            <field name="res_model">master.registration</field>
            <field name="view_mode">tree,form</field>
            <field name="view_id" ref="master_registration_view_tree"/>
            <field name="search_view_id" ref="view_master_registration_filter"/>
            <field name="domain">[]</field>
            <field name="context">{'search_default_today' : 1}</field>
            <field name="help" type="html">
                <p></p>
            </field>
        </record>

        <record id="master_registration_action_tree" model="ir.actions.act_window.view">
            <field eval="1" name="sequence"/>
            <field name="view_mode">tree</field>
            <field name="view_id" ref="master_registration_view_tree"/>
            <field name="act_window_id" ref="master_registration_action"/>
        </record>

        <record id="master_registration_action_form" model="ir.actions.act_window.view">
            <field eval="2" name="sequence"/>
            <field name="view_mode">form</field>
            <field name="view_id" ref="master_registration_view_form"/>
            <field name="act_window_id" ref="master_registration_action"/>
        </record>

        <record id="master_registration_action_dashboard_list" model="ir.actions.act_window">
            <field name="name">Daftar Registrasi</field>
            <field name="type">ir.actions.act_window</field>
            <field name="res_model">master.registration</field>
            <field name="view_mode">tree,form</field>
            <field name="view_id" ref="master_registration_view_tree"/>
            <field name="search_view_id" ref="view_master_registration_filter"/>
            <field name="domain">[]</field>
            <field name="target">main</field>
            <field name="help" type="html">
               <p></p>
            </field>
        </record>

        <record id="master_registration_action_dashboard_list_tree" model="ir.actions.act_window.view">
            <field eval="1" name="sequence"/>
            <field name="view_mode">tree</field>
            <field name="view_id" ref="master_registration_view_tree"/>
            <field name="act_window_id" ref="master_registration_action_dashboard_list"/>
        </record>

        <record id="master_registration_action_dashboard_list_form" model="ir.actions.act_window.view">
            <field eval="2" name="sequence"/>
            <field name="view_mode">form</field>
            <field name="view_id" ref="master_registration_view_form"/>
            <field name="act_window_id" ref="master_registration_action_dashboard_list"/>
        </record>
    
    </data>
</odoo>
